{
  "books": [
    {
      "id": "0d2646b0-b4da-487d-874d-0bebccd50670",
      "name": "Harry Potter",
      "author": "Rowling, J.K.",
      "genre": "Adventure",
      "releaseYear": 2000,
      "description": "Nice book",
      "startReading": "2017-05-24",
      "finishReading": "2018-05-24",
      "status": "Unread",
      "grade": null
    },
    {
      "id": "0d655d62-cf0b-4d6f-8551-2fc5a03d9ab0",
      "name": "One Hundred Years of Solitude",
      "author": "Marquez",
      "genre": "Drama",
      "releaseYear": 1967,
      "description": "No clue",
      "startReading": "2017-05-24",
      "finishReading": "",
      "status": "Unread",
      "grade": null
    },
    {
      "id": "8d2c8a97-feff-4ac0-b53c-077124244251",
      "name": "Tom Sawyer",
      "author": "Twain Mark",
      "genre": "Adventure",
      "releaseYear": 1868,
      "description": "Classic",
      "startReading": "01-01-2022",
      "finishReading": "",
      "status": "In-Progress",
      "grade": null
    },
    {
      "id": "d1e3adbb-f329-4a90-9f65-54ab0d67fdd3",
      "name": "The Divine Comedy",
      "author": "Dante Alighieri",
      "genre": "Drama",
      "releaseYear": 1315,
      "description": "Some text here",
      "startReading": "01-01-2022",
      "finishReading": "01-02-2022",
      "status": "Finished",
      "grade": 4
    },
    {
      "id": "20f68b5d-e4fd-4fca-9e3a-63ff8031332d",
      "name": "Decameron",
      "author": "Giovanni Boccaccio",
      "genre": "Drama",
      "releaseYear": 1024,
      "description": "I have run out of ideas",
      "startReading": "01-01-2022",
      "finishReading": "02-02-2022",
      "status": "Finished",
      "grade": 5
    },
    {
      "id": "888f1fb9-9a8e-4590-9729-6e4686c2919",
      "name": "Crime and Punishment",
      "author": "Fyodor Dostoevsky",
      "genre": "Crime",
      "releaseYear": 1866,
      "description": "Test Description",
      "startReading": "01-01-2022",
      "finishReading": "01-02-2022",
      "status": "finished",
      "grade": 3
    },
    {
      "id": "636a36f2-76eb-490b-abfd-3f13adbfa0d7",
      "name": "Iliad",
      "author": "Homer",
      "genre": "Epic",
      "releaseYear": -735,
      "description": "Not written by Homer Simpson",
      "startReading": "01-01-2022",
      "finishReading": "",
      "status": "Unread",
      "grade": 3
    },
    {
      "id": "3cdc9aad-2300-441f-87b7-4259145f74ab",
      "name": "The Trial",
      "author": "Franz Kafka",
      "genre": "Drama",
      "releaseYear": 1925,
      "description": "Booksssssss",
      "startReading": "01-01-2022",
      "finishReading": "03-02-2022",
      "status": "Finished",
      "grade": 5
    },
    {
      "id": "a98f88ac-3263-42a1-9181-bf60216525e2",
      "name": "Moby Dick",
      "author": "Herman Melville",
      "genre": "Adventure",
      "releaseYear": 1851,
      "description": "Whale whale whale...",
      "startReading": "2021-12-31",
      "finishReading": "2022-02-17T22:00:00.000Z",
      "status": "In-Progress",
      "grade": null
    },
    {
      "id": "1da74a0e-4751-43bc-a2ad-61e90b9adc1d",
      "name": "Metamorphosis",
      "author": "Franz Kafka",
      "genre": "Novella",
      "releaseYear": "1915",
      "description": "",
      "startReading": "2022-01-31T22:00:00.000Z",
      "finishReading": "2022-02-10T22:00:00.000Z",
      "status": "Finished",
      "grade": "4"
    }
  ]
}